INSTALL.rst
LICENSE
MANIFEST.in
README.rst
requirements.txt
setup.cfg
setup.py
src/hyperpython/__init__.py
src/hyperpython/conftest.py
src/hyperpython/core.py
src/hyperpython/fragment.py
src/hyperpython/helpers.py
src/hyperpython/html.py
src/hyperpython/jinja2.py
src/hyperpython/tags.py
src/hyperpython.egg-info/PKG-INFO
src/hyperpython.egg-info/SOURCES.txt
src/hyperpython.egg-info/dependency_links.txt
src/hyperpython.egg-info/not-zip-safe
src/hyperpython.egg-info/requires.txt
src/hyperpython.egg-info/top_level.txt
src/hyperpython/components/__init__.py
src/hyperpython/components/data.py
src/hyperpython/components/fa_icons.py
src/hyperpython/components/hyperlinks.py
src/hyperpython/components/icons.py
src/hyperpython/components/page.py
src/hyperpython/components/text.py
src/hyperpython/contrib/__init__.py
src/hyperpython/contrib/chota.py
src/hyperpython/contrib/milligram.py
src/hyperpython/contrib/pure.py
src/hyperpython/contrib/skeleton.py
src/hyperpython/contrib/bootstrap/__init__.py
src/hyperpython/contrib/foundation/__init__.py
src/hyperpython/contrib/semantic/__init__.py
src/hyperpython/contrib/semantic/base.py
src/hyperpython/contrib/semantic/button.py
src/hyperpython/contrib/semantic/cdn.py
src/hyperpython/contrib/uikit/__init__.py
src/hyperpython/django/__init__.py
src/hyperpython/django/components.py
src/hyperpython/django/conftest.py
src/hyperpython/renderers/__init__.py
src/hyperpython/renderers/attrs.py
src/hyperpython/renderers/helpers.py
src/hyperpython/renderers/single_attr.py
src/hyperpython/utils/__init__.py
src/hyperpython/utils/role_dispatch.py
src/hyperpython/utils/sequences.py
src/hyperpython/utils/text.py