Metadata-Version: 2.1
Name: hyperpython
Version: 1.1.0
Summary: Create HTML data structures using Python functions.
Home-page: https://github.com/fabiommendes/hyperpython/
Author: Fábio Macêdo Mendes
Author-email: fabiomacedomendes@gmail.com
License: BSD License (BSD)
Keywords: web, html, templating
Platform: UNKNOWN
Classifier: Development Status :: 4 - Beta
Classifier: Environment :: Web Environment
Classifier: Framework :: Django
Classifier: Intended Audience :: Developers
Classifier: License :: OSI Approved :: BSD License
Classifier: Programming Language :: Python
Classifier: Programming Language :: Python :: 3
Classifier: Programming Language :: Python :: 3.6
Classifier: Programming Language :: Python :: 3.7
Classifier: Operating System :: OS Independent
Classifier: Topic :: Internet :: WWW/HTTP
Classifier: Topic :: Internet :: WWW/HTTP :: Dynamic Content
Classifier: Topic :: Software Development :: Libraries :: Application Frameworks
Classifier: Topic :: Software Development :: Libraries :: Python Modules
Provides-Extra: docs
Provides-Extra: extra
Provides-Extra: dev
